[
    {
        "price": "5 900",
        "brand": "The Cave",
        "item_type": "Комбинезон Siberian",
        "sizes": [
            "46/48",
            "48/50",
            "50/52",
            "52/54",
            "54/56",
            "56/58"
        ]
    },
    {
        "price": "6 400",
        "brand": "The Cave",
        "item_type": "Комбинезон Fresh",
        "sizes": [
            "46/48",
            "48/50",
            "50/52",
            "52/54",
            "54/56",
            "56/58"
        ]
    },
    {
        "price": "9 093",
        "brand": "Sayonara Boy",
        "item_type": "Комбинезон",
        "sizes": [
            "42/44",
            "44/46",
            "46/48",
            "48/50",
            "50/52",
            "52/54",
            "54/56"
        ]
    },
    {
        "price": "5 900",
        "brand": "The Cave",
        "item_type": "Комбинезон Siberian",
        "sizes": [
            "46/48",
            "48/50",
            "50/52",
            "52/54",
            "54/56",
            "56/58"
        ]
    },
    {
        "price": "13 993",
        "brand": "Sayonara Boy",
        "item_type": "Комбинезон",
        "sizes": [
            "44/46",
            "46/48",
            "48/50",
            "50/52",
            "52/54"
        ]
    },
    {
        "price": "13 993",
        "brand": "Sayonara Boy",
        "item_type": "Комбинезон",
        "sizes": [
            "44/46",
            "46/48",
            "48/50",
            "50/52",
            "52/54"
        ]
    },
    {
        "price": "5 900",
        "brand": "The Cave",
        "item_type": "Комбинезон Siberian",
        "sizes": [
            "48/50",
            "50/52",
            "52/54",
            "54/56",
            "56/58"
        ]
    },
    {
        "price": "6 900",
        "brand": "The Cave",
        "item_type": "Комбинезон Urban",
        "sizes": [
            "46/48",
            "48/50",
            "50/52",
            "52/54",
            "54/56",
            "56/58"
        ]
    },
    {
        "price": "4 900",
        "brand": "The Cave",
        "item_type": "Комбинезон",
        "sizes": [
            "46/48",
            "48/50",
            "50/52",
            "52/54",
            "54/56",
            "56/58"
        ]
    },
    {
        "price": "5 900",
        "brand": "The Cave",
        "item_type": "Комбинезон Siberian",
        "sizes": [
            "48/50",
            "50/52",
            "52/54",
            "54/56",
            "56/58"
        ]
    },
    {
        "price": "7 480",
        "brand": "Oakley",
        "item_type": "Комбинезон ENDURANCE BIB 2.0",
        "sizes": [
            "46/48",
            "48/50",
            "52/54"
        ]
    },
    {
        "price": "6 900",
        "brand": "The Cave",
        "item_type": "Комбинезон Urban",
        "sizes": [
            "46/48",
            "48/50",
            "50/52",
            "52/54",
            "54/56",
            "56/58"
        ]
    },
    {
        "price": "5 900",
        "brand": "The Cave",
        "item_type": "Комбинезон Siberian",
        "sizes": [
            "46/48",
            "48/50",
            "52/54",
            "54/56",
            "56/58"
        ]
    },
    {
        "price": "8 540",
        "brand": "Billabong",
        "item_type": "Комбинезон сноубордический NORTH WEST STX BIB",
        "sizes": [
            "46/48",
            "48/50",
            "50/52"
        ]
    },
    {
        "price": "4 490",
        "brand": "The Cave",
        "item_type": "Комбинезон OverSize",
        "sizes": [
            "50/52",
            "52/54"
        ]
    },
    {
        "price": "6 400",
        "brand": "The Cave",
        "item_type": "Комбинезон Fresh",
        "sizes": [
            "46/48",
            "48/50",
            "50/52",
            "52/54",
            "54/56",
            "56/58"
        ]
    },
    {
        "price": "20 993",
        "brand": "Sayonara Boy",
        "item_type": "Комбинезон",
        "sizes": [
            "42/44",
            "44/46",
            "46/48",
            "48/50",
            "50/52",
            "52/54",
            "54/56"
        ]
    },
    {
        "price": "49 620",
        "brand": "Vivienne Westwood",
        "item_type": "Комбинезон",
        "sizes": [
            "48",
            "50",
            "54"
        ]
    },
    {
        "price": "8 540",
        "brand": "Billabong",
        "item_type": "Комбинезон сноубордический NORTH WEST STX BIB",
        "sizes": [
            "46/48",
            "48/50",
            "50/52"
        ]
    },
    {
        "price": "4 900",
        "brand": "The Cave",
        "item_type": "Комбинезон Basic 2.0",
        "sizes": [
            "46/48",
            "48/50",
            "50/52",
            "52/54",
            "54/56",
            "56/58"
        ]
    },
    {
        "price": "3 540",
        "brand": "The Cave",
        "item_type": "Комбинезон Pilot",
        "sizes": [
            "48/50",
            "50/52",
            "52/54",
            "54/56"
        ]
    },
    {
        "price": "5 400",
        "brand": "The Cave",
        "item_type": "Комбинезон Country",
        "sizes": [
            "46/48",
            "48/50",
            "50/52",
            "52/54",
            "54/56",
            "56/58"
        ]
    },
    {
        "price": "6 660",
        "brand": "Cleo",
        "item_type": "Комбинезон",
        "sizes": [
            "50",
            "52",
            "54",
            "56",
            "58"
        ]
    },
    {
        "price": "3 240",
        "brand": "adidas Combat",
        "item_type": "Трико Wrestling Solid Singlet",
        "sizes": [
            "40/42",
            "44/46",
            "48/50",
            "52/54",
            "56/58",
            "60/62"
        ]
    },
    {
        "price": "3 540",
        "brand": "The Cave",
        "item_type": "Комбинезон Pilot",
        "sizes": [
            "50/52",
            "52/54"
        ]
    },
    {
        "price": "7 349",
        "brand": "Oakley",
        "item_type": "Комбинезон ICON BIB 2.0",
        "sizes": [
            "46/48",
            "48/50",
            "50/52"
        ]
    },
    {
        "price": "6 660",
        "brand": "Cleo",
        "item_type": "Комбинезон",
        "sizes": [
            "50",
            "52",
            "54",
            "56",
            "58"
        ]
    },
    {
        "price": "3 490",
        "brand": "adidas Combat",
        "item_type": "Трико Wrestling Solid Singlet",
        "sizes": [
            "40/42",
            "44/46",
            "48/50",
            "52/54",
            "56/58"
        ]
    },
    {
        "price": "5 900",
        "brand": "The Cave",
        "item_type": "Комбинезон Siberian",
        "sizes": [
            "46/48",
            "48/50",
            "50/52",
            "52/54",
            "54/56",
            "56/58"
        ]
    },
    {
        "price": "8 540",
        "brand": "Billabong",
        "item_type": "Комбинезон горнолыжный NORTH WEST STX BIB",
        "sizes": [
            "46/48",
            "48/50",
            "50/52",
            "52/54"
        ]
    },
    {
        "price": "20 993",
        "brand": "Sayonara Boy",
        "item_type": "Комбинезон",
        "sizes": [
            "42/44",
            "44/46",
            "46/48",
            "48/50",
            "50/52",
            "52/54",
            "54/56"
        ]
    },
    {
        "price": "6 900",
        "brand": "The Cave",
        "item_type": "Комбинезон Urban",
        "sizes": [
            "46/48",
            "48/50",
            "50/52",
            "52/54",
            "54/56",
            "56/58"
        ]
    },
    {
        "price": "13 490",
        "brand": "Billabong",
        "item_type": "Комбинезон горнолыжный FULLER SUIT",
        "sizes": [
            "46/48"
        ]
    },
    {
        "price": "6 900",
        "brand": "The Cave",
        "item_type": "Комбинезон Urban",
        "sizes": [
            "46/48",
            "48/50",
            "50/52",
            "52/54",
            "54/56",
            "56/58"
        ]
    },
    {
        "price": "6 400",
        "brand": "The Cave",
        "item_type": "Комбинезон Fresh",
        "sizes": [
            "46/48",
            "48/50",
            "50/52",
            "52/54"
        ]
    },
    {
        "price": "4 900",
        "brand": "The Cave",
        "item_type": "Комбинезон",
        "sizes": [
            "46/48",
            "48/50",
            "50/52",
            "52/54",
            "54/56",
            "56/58"
        ]
    },
    {
        "price": "4 900",
        "brand": "The Cave",
        "item_type": "Комбинезон Basic 2.0",
        "sizes": [
            "46/48",
            "48/50",
            "50/52",
            "52/54",
            "54/56",
            "56/58"
        ]
    },
    {
        "price": "12 230",
        "brand": "Quiksilver",
        "item_type": "Комбинезон горнолыжный",
        "sizes": [
            "46/48"
        ]
    }
]